setup.py
pyhdhomerun/__init__.py
pyhdhomerun/adapter.py
pyhdhomerun/constants.py
pyhdhomerun/externals.py
pyhdhomerun/hdhr.py
pyhdhomerun/log_config.py
pyhdhomerun/types.py
pyhdhomerun/utility.py
pyhdhomerun.egg-info/PKG-INFO
pyhdhomerun.egg-info/SOURCES.txt
pyhdhomerun.egg-info/dependency_links.txt
pyhdhomerun.egg-info/entry_points.txt
pyhdhomerun.egg-info/requires.txt
pyhdhomerun.egg-info/top_level.txt
pyhdhomerun.egg-info/zip-safe