Metadata-Version: 1.1
Name: pyhdhomerun
Version: 2.3.4
Summary: HDHomeRun interface library.
Home-page: https://github.com/dsoprea/PyHdHomeRun
Author: Dustin Oprea
Author-email: myselfasunder@gmail.com
License: New BSD
Keywords: tv television tuner tvtuner hdhomerun
Platform: UNKNOWN
Classifier: Development Status :: 4 - Beta
Classifier: License :: OSI Approved :: BSD License
Classifier: Natural Language :: English
Classifier: Programming Language :: Python :: 2.7
Classifier: Topic :: Software Development :: Libraries :: Python Modules
Classifier: Topic :: Multimedia :: Video :: Capture
